pylocres/__init__.py
pylocres/city_hash.py
pylocres/cli.py
pylocres/crc_hash.py
pylocres/file_io.py
pylocres/locmeta.py
pylocres/locres.py
pylocres-0.1.6.dist-info/METADATA
pylocres-0.1.6.dist-info/WHEEL
pylocres-0.1.6.dist-info/entry_points.txt
pylocres-0.1.6.dist-info/top_level.txt
pylocres-0.1.6.dist-info/RECORD
