Metadata-Version: 2.4
Name: pylocres
Version: 0.1.6
Summary: Python library for working with Unreal Engine .locres translation files. 
Author-email: stas96111 <stas96111@gmail.com>
License: MIT License
Project-URL: Homepage, https://github.com/stas96111/pylocres
Classifier: Programming Language :: Python :: 3
Classifier: Operating System :: OS Independent
Requires-Python: >=3.8
Requires-Dist: click>=8.2
Requires-Dist: polib>=1.2
